interpretability/BOA.py
interpretability/BOACLASS.py
interpretability/CORELS.py
interpretability/CORELSCLASS.py
interpretability/SLIMCLASS.py
interpretability/SLIMCode.py
interpretability/__init__.py
interpretability/outdated_testfile.py
interpretability/test.py
interpretability/model/__init__.py
interpretability/model/BOA/BOA.py
interpretability/model/BOA/__init__.py
interpretability/model/BOA/dataMaker.py
interpretability/model/CORELS/__init__.py
interpretability/model/CORELS/dataMaker.py
interpretability/model/SLIM/__init__.py
interpretability/model/SLIM/train.py
interpretability/model/SLIM/slim/SLIMCoefficientConstraints.py
interpretability/model/SLIM/slim/__init__.py
interpretability/model/SLIM/slim/create_slim_IP.py
interpretability/model/SLIM/slim/helper_functions.py
resetInterpretability/__init__.py
resetInterpretability/test.py
resetInterpretability/model/Model.py
resetInterpretability/model/__init__.py
resetInterpretability/model/BOA/BOA.py
resetInterpretability/model/BOA/__init__.py
resetInterpretability/model/BOA/dataMaker.py
resetInterpretability/model/CORELS/CORELS.py
resetInterpretability/model/CORELS/__init__.py
resetInterpretability/model/CORELS/dataMaker.py
resetInterpretability/model/SLIM/SLIMCode.py
resetInterpretability/model/SLIM/__init__.py
resetInterpretability/model/SLIM/train.py
resetInterpretability/model/SLIM/slim/SLIMCoefficientConstraints.py
resetInterpretability/model/SLIM/slim/__init__.py
resetInterpretability/model/SLIM/slim/create_slim_IP.py
resetInterpretability/model/SLIM/slim/helper_functions.py
Interpretability-0.0.3.dist-info/LICENSE
Interpretability-0.0.3.dist-info/METADATA
Interpretability-0.0.3.dist-info/WHEEL
Interpretability-0.0.3.dist-info/top_level.txt
Interpretability-0.0.3.dist-info/RECORD
